embedded_text/__init__.py
embedded_text/embedded_text.py
embedded_text-0.0.3.dist-info/licenses/LICENSE
embedded_text-0.0.3.dist-info/METADATA
embedded_text-0.0.3.dist-info/WHEEL
embedded_text-0.0.3.dist-info/entry_points.txt
embedded_text-0.0.3.dist-info/top_level.txt
embedded_text-0.0.3.dist-info/RECORD
