Metadata-Version: 2.4
Name: embedded-text
Version: 0.0.3
Summary: Tool for extracting embedded text data in python script.
Author-email: Nanigashi Uji <53845049+nanigashi-uji@users.noreply.github.com>, Nanigashi Uji <4423013-nanigashi_uji@users.noreply.gitlab.com>
Maintainer-email: Nanigashi Uji <53845049+nanigashi-uji@users.noreply.github.com>, Nanigashi Uji <4423013-nanigashi_uji@users.noreply.gitlab.com>
License: BSD 3-Clause License
Project-URL: Homepage, https://github.com/nanigashi-uji/embedded-text
Keywords: template,development
Classifier: Development Status :: 2 - Pre-Alpha
Classifier: Programming Language :: Python
Classifier: Programming Language :: Python :: 3
Classifier: Programming Language :: Python :: 3.9
Classifier: Programming Language :: Python :: 3.10
Classifier: Programming Language :: Python :: 3.11
Classifier: Programming Language :: Python :: 3.12
Classifier: Programming Language :: Python :: 3.13
Classifier: Topic :: Software Development
Classifier: Topic :: Utilities
Requires-Python: >=3.9
License-File: LICENSE
Dynamic: license-file
